grimo/README_USAGE.md
grimo/__init__.py
grimo/argparse_multi.py
grimo/auth.py
grimo/cli.py
grimo/core.py
grimo/def_trans.md
grimo/package.py
grimo/req_cli.md
grimo/req_readme.md
grimo/storage.py
grimo/utils.py
grimo/i18n/README.md
grimo/i18n/claude.md
grimo/i18n/def_trans_readme.md
grimo/i18n/def_translation.md
grimo/i18n/exe_trans_read.py
grimo/i18n/exe_translation.py
grimo/i18n/message.ar.yml
grimo/i18n/message.bn.yml
grimo/i18n/message.da.yml
grimo/i18n/message.de.yml
grimo/i18n/message.en.yml
grimo/i18n/message.es.yml
grimo/i18n/message.fa.yml
grimo/i18n/message.fi.yml
grimo/i18n/message.fr.yml
grimo/i18n/message.hi.yml
grimo/i18n/message.it.yml
grimo/i18n/message.ja.yml
grimo/i18n/message.ko.yml
grimo/i18n/message.nl.yml
grimo/i18n/message.no.yml
grimo/i18n/message.pl.yml
grimo/i18n/message.pt.yml
grimo/i18n/message.ru.yml
grimo/i18n/message.sv.yml
grimo/i18n/message.th.yml
grimo/i18n/message.tr.yml
grimo/i18n/message.uk.yml
grimo/i18n/message.vi.yml
grimo/i18n/message.zh.yml
grimo/i18n/multilang.md
grimo/i18n/openai-gpt4o
grimo/i18n/readme_rich_progress.png
grimo-1.3.46.dist-info/LICENSE
grimo-1.3.46.dist-info/METADATA
grimo-1.3.46.dist-info/WHEEL
grimo-1.3.46.dist-info/entry_points.txt
grimo-1.3.46.dist-info/top_level.txt
grimo-1.3.46.dist-info/RECORD
