Metadata-Version: 2.1
Name: grimo
Version: 1.3.46
Summary: Abstract Programming Language Package Manager
Home-page: https://github.com/dai-motoki/grimo
Author: dai motoki
Author-email: dai.motoki@gmail.com
Classifier: Development Status :: 3 - Alpha
Classifier: Intended Audience :: Developers
Classifier: License :: OSI Approved :: MIT License
Classifier: Programming Language :: Python :: 3
Classifier: Programming Language :: Python :: 3.7
Classifier: Programming Language :: Python :: 3.8
Classifier: Programming Language :: Python :: 3.9
Classifier: Programming Language :: Python :: 3.10
License-File: LICENSE
Requires-Dist: requests
Requires-Dist: click
Requires-Dist: colorama
Requires-Dist: boto3
Requires-Dist: streamlit
Requires-Dist: aiohttp
Requires-Dist: aiofiles
Requires-Dist: i18nice[yaml]
